yasg_util/__init__.py
yasg_util-0.2.0.dist-info/LICENSE
yasg_util-0.2.0.dist-info/METADATA
yasg_util-0.2.0.dist-info/WHEEL
yasg_util-0.2.0.dist-info/top_level.txt
yasg_util-0.2.0.dist-info/RECORD
