Metadata-Version: 2.1
Name: yasg-util
Version: 0.2.0
Summary: Injecting parameters through annotations based on drf-yasg
Home-page: https://github.com/ShangSky/yasg-util
Author: shangsky
Author-email: t_c_y@outlook.com
Maintainer: shangsky
Maintainer-email: t_c_y@outlook.com
License: MIT
Platform: all
Classifier: Development Status :: 4 - Beta
Classifier: Operating System :: OS Independent
Classifier: Intended Audience :: Developers
Classifier: License :: OSI Approved :: MIT License
Classifier: Programming Language :: Python :: 3.6
Classifier: Programming Language :: Python :: 3.7
Classifier: Programming Language :: Python :: 3.8
Classifier: Programming Language :: Python :: 3.9
Classifier: Topic :: Software Development :: Libraries
Requires-Python: >=3.6
License-File: LICENSE
Requires-Dist: drf-yasg
